{
  "__comment": "Model generated using MrCrayfish's Model Creator (http://mrcrayfish.com/modelcreator/)",
  "textures": {
    "0": "herobrine:item/plaque_ardoise_atlas",
    "particle": "#0"
  },
  "gui_light": "front",
  "elements": [
    {
      "from": [4, 6, 8],
      "to": [12, 14, 9],
      "faces": {
        "north": {
          "texture": "#0",
          "uv": [0, 0, 16, 16]
        },
        "east": {
          "texture": "#0",
          "uv": [0, 0, 16, 16]
        },
        "south": {
          "texture": "#0",
          "uv": [0, 0, 16, 16]
        },
        "west": {
          "texture": "#0",
          "uv": [0, 0, 16, 16]
        },
        "up": {
          "texture": "#0",
          "uv": [0, 0, 16, 16]
        },
        "down": {
          "texture": "#0",
          "uv": [0, 0, 16, 16]
        }
      }
    }
  ]
}