{"textures":{"0":"bettermodel:item/demon_knight_demon_knight","particle":"bettermodel:item/demon_knight_demon_knight"},"elements":[{"from":[-0.40756702,15.883752,0.5993357],"to":[2.592433,20.38375,5.099336],"faces":{"north":{"uv":[10.625,5.25,11.0,5.875],"tintindex":0,"texture":"#0"},"east":{"uv":[5.875,7.875,6.5,8.5],"tintindex":0,"texture":"#0"},"south":{"uv":[6.5,10.625,6.875,11.25],"tintindex":0,"texture":"#0"},"west":{"uv":[6.5,7.875,7.125,8.5],"tintindex":0,"texture":"#0"},"up":{"uv":[11.0,10.375,10.625,9.75],"tintindex":0,"texture":"#0"},"down":{"uv":[6.25,10.75,5.875,11.375],"tintindex":0,"texture":"#0"}}}],"display":{"fixed":{"rotation":[7.7293954,13.814705,-11.59644]}}}