{"textures":{"0":"bettermodel:item/mf_ember_claw_leap_fall_break_mf_ember_claw_leap_fall_break","particle":"bettermodel:item/mf_ember_claw_leap_fall_break_mf_ember_claw_leap_fall_break"},"elements":[{"from":[7.95,7.95,7.95],"to":[7.96,7.96,7.96],"faces":{"north":{"uv":[0.0,0.0,0.125,0.0],"tintindex":0,"texture":"#0"},"east":{"uv":[0.0,0.0,0.125,0.0],"tintindex":0,"texture":"#0"},"south":{"uv":[0.0,0.0,0.125,0.0],"tintindex":0,"texture":"#0"},"west":{"uv":[0.0,0.0,0.125,0.0],"tintindex":0,"texture":"#0"},"up":{"uv":[10.375,7.875,10.25,7.75],"tintindex":0,"texture":"#0"},"down":{"uv":[10.375,7.875,10.25,8.0],"tintindex":0,"texture":"#0"}}}]}