{"textures":{"0":"bettermodel:item/scene_townsfolk_5_pose_1_npc_skin_1__replaceable","particle":"bettermodel:item/scene_townsfolk_5_pose_1_npc_skin_1__replaceable"},"elements":[{"from":[7.05,-1.5,6.1],"to":[10.85,9.9,9.9],"faces":{"north":{"uv":[11.0,5.0,12.0,8.0],"tintindex":0,"texture":"#0"},"east":{"uv":[10.0,5.0,11.0,8.0],"tintindex":0,"texture":"#0"},"south":{"uv":[13.0,5.0,14.0,8.0],"tintindex":0,"texture":"#0"},"west":{"uv":[12.0,5.0,13.0,8.0],"tintindex":0,"texture":"#0"},"up":{"uv":[12.0,5.0,11.0,4.0],"tintindex":0,"texture":"#0"},"down":{"uv":[13.0,4.0,12.0,5.0],"tintindex":0,"texture":"#0"}}}]}