{"textures":{"0":"bettermodel:item/vfx_ice_knight_blood_impact_vfx_blood_impact","particle":"bettermodel:item/vfx_ice_knight_blood_impact_vfx_blood_impact"},"elements":[{"from":[6.5,6.5,6.5],"to":[9.5,9.5,9.5],"faces":{"north":{"uv":[8.0,0.0,9.5,1.5],"tintindex":0,"texture":"#0"},"east":{"uv":[9.5,0.0,8.0,1.5],"tintindex":0,"texture":"#0"},"south":{"uv":[8.0,0.0,9.5,1.5],"tintindex":0,"texture":"#0"},"west":{"uv":[9.5,0.0,8.0,1.5],"tintindex":0,"texture":"#0"},"up":{"uv":[9.5,0.0,8.0,1.5],"tintindex":0,"texture":"#0"},"down":{"uv":[9.5,0.0,8.0,1.5],"tintindex":0,"texture":"#0"}}}]}